{
  "reset": {
    "zero_ablation": {
      "induction": {
        "nll": {
          "ACDC": {
            "score": [
              Infinity,
              1,
              0.63096,
              0.39811,
              0.25119,
              0.15849,
              0.1,
              0.0631,
              0.03981,
              0.02512,
              0.01585,
              0.01,
              0.00631,
              0.00398,
              0.00251,
              0.00158,
              0.001,
              0.00063,
              0.0004,
              0.00025,
              0.00016,
              0.0001,
              -Infinity
            ],
            "test_kl_div": [
              Infinity,
              10.38847541809082,
              8.7196626663208,
              8.7196626663208,
              8.7196626663208,
              8.7196626663208,
              8.999244689941406,
              9.340546607971191,
              9.340546607971191,
              9.340546607971191,
              9.754435539245605,
              9.47427749633789,
              9.47427749633789,
              9.47427749633789,
              9.47427749633789,
              9.47427749633789,
              9.47427749633789,
              9.47427749633789,
              9.47427749633789,
              9.47427749633789,
              9.47427749633789,
              9.47427749633789,
              -Infinity
            ],
            "test_nll": [
              Infinity,
              11.544164657592773,
              9.778353691101074,
              9.778353691101074,
              9.778353691101074,
              9.778353691101074,
              10.181151390075684,
              10.508031845092773,
              10.508031845092773,
              10.508031845092773,
              10.90816593170166,
              10.646924018859863,
              10.646924018859863,
              10.646924018859863,
              10.646924018859863,
              10.646924018859863,
              10.646924018859863,
              10.646924018859863,
              10.646924018859863,
              10.646924018859863,
              10.646924018859863,
              10.646924018859863,
              -Infinity
            ],
            "test_match_nll": [
              Infinity,
              10.530407905578613,
              8.764596939086914,
              8.764596939086914,
              8.764596939086914,
              8.764596939086914,
              9.16739273071289,
              9.494272232055664,
              9.494272232055664,
              9.494274139404297,
              9.894407272338867,
              9.63316535949707,
              9.63316535949707,
              9.63316535949707,
              9.63316535949707,
              9.63316535949707,
              9.63316535949707,
              9.63316535949707,
              9.63316535949707,
              9.63316535949707,
              9.63316535949707,
              9.63316535949707,
              -Infinity
            ],
            "n_edges": [
              NaN,
              2,
              3,
              3,
              4,
              4,
              11,
              13,
              13,
              15,
              16,
              20,
              20,
              20,
              20,
              20,
              20,
              20,
              20,
              20,
              20,
              20,
              NaN
            ],
            "n_nodes": [
              NaN,
              3,
              5,
              5,
              6,
              6,
              12,
              15,
              15,
              19,
              17,
              24,
              24,
              24,
              24,
              24,
              24,
              24,
              24,
              24,
              24,
              24,
              NaN
            ]
          }
        }
      }
    }
  }
}