{
  "trained": {
    "random_ablation": {
      "docstring": {
        "docstring_metric": {
          "ACDC": {
            "test_match_nll": [
              Infinity,
              0,
              0,
              0,
              0,
              0,
              0,
              0,
              0,
              0,
              0,
              0,
              0,
              0,
              0,
              0,
              0,
              0,
              0,
              0,
              0,
              0,
              0,
              0,
              0,
              0,
              0,
              -Infinity
            ],
            "test_docstring_stefan": [
              Infinity,
              -0.6599999666213989,
              -0.6599999666213989,
              -0.6599999666213989,
              -0.6599999666213989,
              -0.6599999666213989,
              -0.6599999666213989,
              -0.6599999666213989,
              -0.6599999666213989,
              -0.6599999666213989,
              -0.6599999666213989,
              -0.6599999666213989,
              -0.6599999666213989,
              -0.6599999666213989,
              -0.6599999666213989,
              -0.6599999666213989,
              -0.6599999666213989,
              -0.6599999666213989,
              -0.6599999666213989,
              -0.6599999666213989,
              -0.6599999666213989,
              -0.6599999666213989,
              -0.6599999666213989,
              -0.6599999666213989,
              -0.6599999666213989,
              -0.6599999666213989,
              -0.6599999666213989,
              -Infinity
            ],
            "test_nll": [
              Infinity,
              1.5616430044174194,
              1.5616430044174194,
              1.5616430044174194,
              1.5616430044174194,
              1.5616430044174194,
              1.5616430044174194,
              1.5616430044174194,
              1.5616430044174194,
              1.5616430044174194,
              1.5616430044174194,
              1.5616430044174194,
              1.5616430044174194,
              1.5616430044174194,
              1.5616430044174194,
              1.5616430044174194,
              1.5616439580917358,
              1.5616430044174194,
              1.5616430044174194,
              1.5616439580917358,
              1.5616430044174194,
              1.5616439580917358,
              1.5616430044174194,
              1.5616439580917358,
              1.5616430044174194,
              1.5616439580917358,
              1.5616439580917358,
              -Infinity
            ],
            "test_docstring_metric": [
              Infinity,
              -0.8751538395881653,
              -0.8751538395881653,
              -0.8751538395881653,
              -0.8751538395881653,
              -0.8751538395881653,
              -0.8751538395881653,
              -0.8751538395881653,
              -0.8751538395881653,
              -0.8751538395881653,
              -0.8751538395881653,
              -0.8751538395881653,
              -0.8751538395881653,
              -0.8751538395881653,
              -0.8751538395881653,
              -0.8751538395881653,
              -0.8751513957977295,
              -0.8751538395881653,
              -0.8751538395881653,
              -0.8751513957977295,
              -0.8751538395881653,
              -0.8751513957977295,
              -0.8751538395881653,
              -0.8751513957977295,
              -0.8751538395881653,
              -0.8751513957977295,
              -0.8751513957977295,
              -Infinity
            ],
            "score": [
              Infinity,
              1,
              0.63096,
              0.39811,
              0.25119,
              0.15849,
              0.1,
              0.0631,
              0.03981,
              0.02512,
              0.01585,
              0.01,
              0.00631,
              0.00398,
              0.00251,
              0.00158,
              0.001,
              0.001,
              0.00063,
              0.00063,
              0.0004,
              0.0004,
              0.00025,
              0.00025,
              0.00016,
              0.00016,
              0.0001,
              -Infinity
            ],
            "test_kl_div": [
              Infinity,
              0,
              0,
              0,
              0,
              0,
              0,
              0,
              0,
              0,
              0,
              0,
              0,
              0,
              0,
              0,
              0,
              0,
              0,
              0,
              0,
              0,
              0,
              0,
              0,
              0,
              0,
              -Infinity
            ],
            "fpr": [
              0.0,
              0.0,
              0.0007396449704142012,
              0.0073964497041420114,
              0.008875739644970414,
              0.022928994082840236,
              0.03994082840236687,
              0.05473372781065089,
              0.07914201183431953,
              0.10724852071005918,
              0.14644970414201183,
              0.20192307692307693,
              0.2448224852071006,
              0.29659763313609466,
              0.33505917159763315,
              0.371301775147929,
              0.40014792899408286,
              0.40014792899408286,
              0.4223372781065089,
              0.4223372781065089,
              0.4408284023668639,
              0.4408284023668639,
              0.45340236686390534,
              0.45340236686390534,
              0.4578402366863905,
              0.4578402366863905,
              0.46597633136094674,
              1.0
            ],
            "tpr": [
              0.0,
              0.28,
              0.56,
              0.92,
              0.92,
              1.0,
              1.0,
              1.0,
              1.0,
              1.0,
              1.0,
              1.0,
              1.0,
              1.0,
              1.0,
              1.0,
              1.0,
              1.0,
              1.0,
              1.0,
              1.0,
              1.0,
              1.0,
              1.0,
              1.0,
              1.0,
              1.0,
              1.0
            ],
            "precision": [
              1.0,
              1.0,
              0.9333333333333333,
              0.696969696969697,
              0.6571428571428571,
              0.44642857142857145,
              0.31645569620253167,
              0.25252525252525254,
              0.1893939393939394,
              0.14705882352941177,
              0.11210762331838565,
              0.08389261744966443,
              0.0702247191011236,
              0.05868544600938967,
              0.05230125523012552,
              0.04743833017077799,
              0.044169611307420496,
              0.044169611307420496,
              0.04194630872483222,
              0.04194630872483222,
              0.040257648953301126,
              0.040257648953301126,
              0.03918495297805643,
              0.03918495297805643,
              0.03881987577639751,
              0.03881987577639751,
              0.03816793893129771,
              0.0
            ]
          }
        }
      }
    }
  }
}